logger_py/__init__.py
logger_py/logger.py
logger_py/config/__init__.py
logger_py/config/log_config.py
logger_py/config/option.py
logger_py/config/tracer_config.py
logger_py/mylogger/__init__.py
logger_py/mylogger/abstract.py
logger_py/mylogger/my_structlog.py
logger_py/mytracer/__init__.py
logger_py/mytracer/tracer.py
logger_py/utils/__init__.py
logger_py/utils/env.py
everfir_logger-0.2.7.dist-info/METADATA
everfir_logger-0.2.7.dist-info/WHEEL
everfir_logger-0.2.7.dist-info/top_level.txt
everfir_logger-0.2.7.dist-info/RECORD
