Metadata-Version: 2.4
Name: everfir_logger
Version: 0.2.7
Summary: A brief description of your project
Home-page: https://github.com/everfir/logger-py
Author: houyibin
Author-email: houyibin@everfir.com
Classifier: Programming Language :: Python :: 3
Classifier: License :: OSI Approved :: MIT License
Classifier: Operating System :: OS Independent
Requires-Python: >=3.0
Requires-Dist: blinker==1.9.0
Requires-Dist: certifi==2024.8.30
Requires-Dist: charset-normalizer==3.4.0
Requires-Dist: click==8.1.7
Requires-Dist: Deprecated==1.2.15
Requires-Dist: Flask==3.1.0
Requires-Dist: googleapis-common-protos==1.66.0
Requires-Dist: idna==3.10
Requires-Dist: importlib_metadata==8.5.0
Requires-Dist: itsdangerous==2.2.0
Requires-Dist: Jinja2==3.1.4
Requires-Dist: MarkupSafe==3.0.2
Requires-Dist: opentelemetry-api==1.28.1
Requires-Dist: opentelemetry-exporter-otlp-proto-common==1.28.1
Requires-Dist: opentelemetry-exporter-otlp-proto-http==1.28.1
Requires-Dist: opentelemetry-proto==1.28.1
Requires-Dist: opentelemetry-sdk==1.28.1
Requires-Dist: opentelemetry-semantic-conventions==0.49b1
Requires-Dist: opentracing==2.4.0
Requires-Dist: protobuf==5.28.3
Requires-Dist: requests==2.32.3
Requires-Dist: setuptools==75.5.0
Requires-Dist: structlog==24.4.0
Requires-Dist: typing_extensions==4.12.2
Requires-Dist: urllib3==2.2.3
Requires-Dist: Werkzeug==3.1.3
Requires-Dist: wrapt==1.16.0
Requires-Dist: zipp==3.21.0
Dynamic: author
Dynamic: author-email
Dynamic: classifier
Dynamic: description
Dynamic: description-content-type
Dynamic: home-page
Dynamic: requires-dist
Dynamic: requires-python
Dynamic: summary
